pureml/__init__.py
pureml/activations.py
pureml/base.py
pureml/evaluation.py
pureml/general_math.py
pureml/layers.py
pureml/logging_util.py
pureml/losses.py
pureml/machinery.py
pureml/optimizers.py
pureml/training_utils.py
pureml/util.py
pureml/datasets/__init__.py
pureml/datasets/MNIST/__init__.py
pureml/datasets/MNIST/dataset.py
pureml/datasets/MNIST/files/__init__.py
pureml/datasets/MNIST/files/mnist-28x28_uint8.zarr.zip
pureml/models/__init__.py
pureml/models/classical/__init__.py
pureml/models/classical/knn.py
pureml/models/neural_networks/__init__.py
pureml/models/neural_networks/mnist_beater.py
ym_pure_ml-1.2.8.dist-info/licenses/LICENSE
ym_pure_ml-1.2.8.dist-info/licenses/NOTICE
ym_pure_ml-1.2.8.dist-info/METADATA
ym_pure_ml-1.2.8.dist-info/WHEEL
ym_pure_ml-1.2.8.dist-info/top_level.txt
ym_pure_ml-1.2.8.dist-info/RECORD
