Metadata-Version: 2.4
Name: ym-pure-ml
Version: 1.2.8
Summary: Transparent, NumPy-only deep learning framework for teaching, small-scale projects, prototyping, and reproducible experiments.
Author: Yehor Mishchyriak
License:                                  Apache License
Project-URL: Homepage, https://github.com/Yehor-Mishchyriak/PureML
Project-URL: Source, https://github.com/Yehor-Mishchyriak/PureML
Project-URL: Tracker, https://github.com/Yehor-Mishchyriak/PureML/issues
Project-URL: Documentation, https://ymishchyriak.com/docs/PUREML-DOCS
Keywords: numpy,deep-learning,autodiff,education
Classifier: Programming Language :: Python :: 3
Classifier: Programming Language :: Python :: 3 :: Only
Classifier: Programming Language :: Python :: 3.11
Classifier: Programming Language :: Python :: 3.12
Classifier: License :: OSI Approved :: Apache Software License
Classifier: Operating System :: OS Independent
Classifier: Topic :: Scientific/Engineering :: Artificial Intelligence
Requires-Python: >=3.11
License-File: LICENSE
License-File: NOTICE
Requires-Dist: numpy>=2.0
Requires-Dist: zarr>=3.1
Provides-Extra: tests
Dynamic: license-file
